lipostdate.py
lipostdate-0.0.1.dist-info/METADATA
lipostdate-0.0.1.dist-info/WHEEL
lipostdate-0.0.1.dist-info/top_level.txt
lipostdate-0.0.1.dist-info/RECORD
