Metadata-Version: 2.1
Name: lipostdate
Version: 0.0.1
Summary: Python package for extracting the exact date from the linkedin post URLs
Home-page: https://github.com/Volcano-Dragon/lipostdate
Author: Garv Saxena
Author-email: garvsaxena185@gmail.com
License: UNKNOWN
Keywords: linkedin,linkedin post dates,linkedin post extraction,linkedin post url
Platform: UNKNOWN
Classifier: Development Status :: 5 - Production/Stable
Classifier: Intended Audience :: Developers
Classifier: Programming Language :: Python :: 2
Classifier: Programming Language :: Python :: 3
Classifier: Operating System :: MacOS :: MacOS X
Classifier: Operating System :: Microsoft :: Windows
